histalign/__about__.py
histalign/__init__.py
histalign/py.typed
histalign/backend/__init__.py
histalign/backend/array_operations/__init__.py
histalign/backend/ccf/__init__.py
histalign/backend/ccf/downloads.py
histalign/backend/ccf/model_view.py
histalign/backend/ccf/paths.py
histalign/backend/io/__init__.py
histalign/backend/io/image_conversions.py
histalign/backend/maths/__init__.py
histalign/backend/models/__init__.py
histalign/backend/models/errors.py
histalign/backend/preprocessing/__init__.py
histalign/backend/quantification/__init__.py
histalign/backend/quantification/quantification_methods.py
histalign/backend/quantification/quantifiers.py
histalign/backend/registration/__init__.py
histalign/backend/registration/alignment.py
histalign/backend/workspace/__init__.py
histalign/frontend/__init__.py
histalign/frontend/common_widgets.py
histalign/frontend/dialogs.py
histalign/frontend/pyside_helpers.py
histalign/frontend/themes.py
histalign/frontend/centralised/__init__.py
histalign/frontend/preprocessing/__init__.py
histalign/frontend/preprocessing/prepare.py
histalign/frontend/preprocessing/results.py
histalign/frontend/qa/__init__.py
histalign/frontend/qa/measures.py
histalign/frontend/qa/viewer.py
histalign/frontend/quantification/__init__.py
histalign/frontend/quantification/analysis_parameters_widgets.py
histalign/frontend/quantification/prepare.py
histalign/frontend/quantification/results.py
histalign/frontend/quantification/view.py
histalign/frontend/quantification/visualisers.py
histalign/frontend/registration/__init__.py
histalign/frontend/registration/alignment.py
histalign/frontend/registration/alpha.py
histalign/frontend/registration/helpers.py
histalign/frontend/registration/settings.py
histalign/frontend/registration/thumbnails.py
histalign/frontend/visualisation/__init__.py
histalign/frontend/visualisation/information.py
histalign/frontend/visualisation/views.py
histalign/resources/icons/2d-folder-icon.svg
histalign-0.0.1.dist-info/METADATA
histalign-0.0.1.dist-info/WHEEL
histalign-0.0.1.dist-info/entry_points.txt
histalign-0.0.1.dist-info/licenses/LICENSE
histalign-0.0.1.dist-info/RECORD
